translatebot_django/__init__.py
translatebot_django/apps.py
translatebot_django/utils.py
translatebot_django/backends/__init__.py
translatebot_django/backends/modeltranslation.py
translatebot_django/management/__init__.py
translatebot_django/management/commands/__init__.py
translatebot_django/management/commands/translate.py
translatebot_django-0.3.6.dist-info/licenses/LICENSE
translatebot_django-0.3.6.dist-info/METADATA
translatebot_django-0.3.6.dist-info/WHEEL
translatebot_django-0.3.6.dist-info/top_level.txt
translatebot_django-0.3.6.dist-info/RECORD
