Metadata-Version: 2.4
Name: translatebot-django
Version: 0.3.6
Summary: Stop copy-pasting to and from Google Translate. Translate your Django .po files automatically with AI.
Author: Bjorn the Builder
Author-email: bjornthebuilder@proton.me
License: MPL-2.0
Project-URL: homepage, https://github.com/gettranslatebot/translatebot-django
Project-URL: documentation, https://translatebot.dev/docs/
Project-URL: repository, https://github.com/gettranslatebot/translatebot-django
Project-URL: issues, https://github.com/gettranslatebot/translatebot-django/issues
Project-URL: changelog, https://github.com/gettranslatebot/translatebot-django/blob/main/CHANGELOG.md
Keywords: django,translation,i18n,localization,gettext,po,openai
Classifier: Development Status :: 3 - Alpha
Classifier: Framework :: Django
Classifier: Framework :: Django :: 4.2
Classifier: Framework :: Django :: 5.0
Classifier: Framework :: Django :: 5.1
Classifier: Framework :: Django :: 5.2
Classifier: Framework :: Django :: 6.0
Classifier: Intended Audience :: Developers
Classifier: License :: OSI Approved :: Mozilla Public License 2.0 (MPL 2.0)
Classifier: Programming Language :: Python :: 3
Classifier: Programming Language :: Python :: 3.10
Classifier: Programming Language :: Python :: 3.11
Classifier: Programming Language :: Python :: 3.12
Classifier: Programming Language :: Python :: 3.13
Classifier: Programming Language :: Python :: 3.14
Classifier: Topic :: Software Development :: Internationalization
Classifier: Topic :: Software Development :: Localization
Requires-Python: >=3.10
License-File: LICENSE
Requires-Dist: Django>=4.2
Requires-Dist: polib>=1.2.0
Requires-Dist: litellm>=1.80.0
Provides-Extra: dev
Requires-Dist: pytest>=7.0.0; extra == "dev"
Requires-Dist: pytest-django>=4.5.0; extra == "dev"
Requires-Dist: pytest-mock>=3.10.0; extra == "dev"
Requires-Dist: pytest-cov>=4.0.0; extra == "dev"
Requires-Dist: ruff>=0.8.0; extra == "dev"
Requires-Dist: django-modeltranslation>=0.18; extra == "dev"
Provides-Extra: modeltranslation
Requires-Dist: django-modeltranslation>=0.18; extra == "modeltranslation"
Dynamic: license-file
